kraken_helper/helper_date.py
kraken_helper/helper_email.py
kraken_helper/helper_url.py
kraken_helper/helper_uuid.py
kraken_helper/kraken_helper.py
kraken_helper-0.0.1.dist-info/LICENSE.txt
kraken_helper-0.0.1.dist-info/METADATA
kraken_helper-0.0.1.dist-info/WHEEL
kraken_helper-0.0.1.dist-info/top_level.txt
kraken_helper-0.0.1.dist-info/RECORD
